pecrs/__init__.py
pecrs/clock.py
pecrs/collider.py
pecrs/index.py
pecrs/shape.py
pecrs/space.py
pecrs/spatialhash.py
pecrs/vector.py
pecrs-0.35.dist-info/LICENSE
pecrs-0.35.dist-info/WHEEL
pecrs-0.35.dist-info/METADATA
pecrs-0.35.dist-info/RECORD
