Metadata-Version: 2.1
Name: pecrs
Version: 0.35
Summary: Pythonic Entity Collision Resolution System
Home-page: https://github.com/solidsmokesoftware/pecrs-py
License: LGPL-3.0
Author: Solid Smoke Software
Author-email: solid.smoke.software@gmail.com
Requires-Python: >=3.6.9,<4.0.0
Classifier: License :: OSI Approved :: GNU Lesser General Public License v3 (LGPLv3)
Classifier: Programming Language :: Python :: 3
Classifier: Programming Language :: Python :: 3.7
Classifier: Programming Language :: Python :: 3.8
